matrixkit/__init__.py
matrixkit/block.py
matrixkit/core.py
matrixkit/generate.py
matrixkit/io.py
matrixkit/metadata.py
matrixkit/plot.py
matrixkit/preconditioning.py
matrixkit/util.py
matrixkit-0.1.2.dist-info/LICENSE
matrixkit-0.1.2.dist-info/METADATA
matrixkit-0.1.2.dist-info/WHEEL
matrixkit-0.1.2.dist-info/top_level.txt
matrixkit-0.1.2.dist-info/RECORD
