Metadata-Version: 2.1
Name: matrixkit
Version: 0.1.2
Summary: Synthetic Matrix Generation for Machine Learning and Scientific Computing
Home-page: https://github.com/AnnaValentinaHirsch/matrixkit
Author: ['Toni Johann Schulze Dieckhoff', 'Anna-Valentina Hirsch']
Author-email: a-valentina.hirsch@hotmail.com
Classifier: Programming Language :: Python :: 3
Classifier: License :: OSI Approved :: Apache Software License
Classifier: Operating System :: OS Independent
Requires-Python: >=3.6
License-File: LICENSE
Requires-Dist: numpy ~=1.26.4
Requires-Dist: scipy ~=1.13.1
Requires-Dist: pillow ~=10.3.0
Requires-Dist: matplotlib ~=3.5.2
Requires-Dist: seaborn ~=0.13.2
